zoritori/__init__.py
zoritori/__main__.py
zoritori/cli.py
zoritori/dictionary.py
zoritori/drawing.py
zoritori/events.py
zoritori/files.py
zoritori/options.py
zoritori/overlay.py
zoritori/pipeline.py
zoritori/platform.py
zoritori/recognizers/exceptions.py
zoritori/recognizers/google_vision.py
zoritori/recognizers/tesseract.py
zoritori/screenshots.py
zoritori/settings.py
zoritori/strings.py
zoritori/tokenizer.py
zoritori/translator.py
zoritori/types.py
zoritori/ui.py
zoritori/vocabulary.py
zoritori/watcher.py
zoritori-0.0.2.post1.dist-info/WHEEL
zoritori-0.0.2.post1.dist-info/entry_points.txt
zoritori-0.0.2.post1.dist-info/LICENSE
zoritori-0.0.2.post1.dist-info/METADATA
zoritori-0.0.2.post1.dist-info/RECORD
