Metadata-Version: 2.1
Name: zoritori
Version: 0.0.2.post1
Summary: yet another tool to help you read text in Japanese video games
Home-page: https://github.com/okonomichiyaki/zoritori
License: MIT
Author: michiaki yamada
Author-email: okonomichiyaki@gmail.com
Requires-Python: >=3.10,<4.0
Classifier: License :: OSI Approved :: MIT License
Classifier: Programming Language :: Python :: 3
Classifier: Programming Language :: Python :: 3.10
Classifier: Programming Language :: Python :: 3.11
Requires-Dist: ConfigArgParse (>=1.5.3,<2.0.0)
Requires-Dist: PyAutoGUI (>=0.9.53,<0.10.0)
Requires-Dist: PyOpenGL (>=3.1.6,<4.0.0)
Requires-Dist: SudachiDict-core (>=20220519,<20220520)
Requires-Dist: SudachiPy (>=0.6.5,<0.7.0)
Requires-Dist: glfw (>=2.5.3,<3.0.0)
Requires-Dist: google-cloud-vision (>=2.7.3,<3.0.0)
Requires-Dist: jamdict ; platform_system != "Windows"
Requires-Dist: jamdict-data ; platform_system != "Windows"
Requires-Dist: jisho-api (>=0.1.8,<0.2.0) ; platform_system == "Windows"
Requires-Dist: opencv-python (>=4.6.0,<5.0.0)
Requires-Dist: pytesseract (>=0.3.9,<0.4.0)
Requires-Dist: pywin32 ; platform_system == "Windows"
Requires-Dist: skia-python (>=87.4,<88.0)
Project-URL: Repository, https://github.com/okonomichiyaki/zoritori
